LICENSE
MANIFEST.in
README.rst
requirements.txt
setup.py
tox.ini
distob/__init__.py
distob/_pylru.py
distob/arrays.py
distob/distob.py
distob.egg-info/PKG-INFO
distob.egg-info/SOURCES.txt
distob.egg-info/dependency_links.txt
distob.egg-info/not-zip-safe
distob.egg-info/pbr.json
distob.egg-info/requires.txt
distob.egg-info/top_level.txt
distob/tests/test_distob.py
docs/Makefile
docs/conf.py
docs/distob.rst
docs/index.rst
docs/make.bat
docs/modules.rst
examples/example_distributed_arrays.py
examples/example_remote_objects.py