Metadata-Version: 1.1
Name: distob
Version: 0.3.0
Summary: Distributed computing made easier, using remote objects
Home-page: http://github.com/mattja/distob/
Author: Matthew J. Aburn
Author-email: mattja6@gmail.com
License: GPLv3+
Platform: any
Classifier: Programming Language :: Python
Classifier: Development Status :: 2 - Pre-Alpha
Classifier: Intended Audience :: Developers
Classifier: License :: OSI Approved :: GNU General Public License (GPL)
Classifier: Operating System :: OS Independent
Classifier: Topic :: Software Development :: Libraries :: Python Modules
Classifier: Topic :: System :: Distributed Computing
